{
  "users": [
    {
      "email": "hassanabdelhamed09@gmail.com",
      "password": "$2a$10$jnAeXx/R7OFTxfeo5yKm/uA7WuGCFiJgWf/dApM6vRoPT8fqUsk2W",
      "username": "Hassan",
      "id": 1
    },
    {
      "email": "ali@gmail.com",
      "password": "$2a$10$6RNPk2hF8DAt1i.5CKKx0e6AQCSgpsjEiujZrI18mIe0AvmWsbzGO",
      "username": "Ali",
      "id": 2
    }
  ],
  "tasks": [
    {
      "id": "564f3db5-8db6-43dc-af20-5a4ca30c3976",
      "userId": 1,
      "title": "new",
      "description": "",
      "priority": "High",
      "dueDate": "2026-04-25",
      "category": "Study",
      "tags": "",
      "isDone": true,
      "createdAt": "2026-04-24T18:50:48.603Z",
      "completedAt": "2026-04-24T18:51:21.248Z"
    },
    {
      "id": "7adddae3-4a03-47bd-b925-191e6ff841d9",
      "userId": 1,
      "title": "new 2",
      "description": "",
      "priority": "Medium",
      "dueDate": "2026-04-24",
      "category": "Personal",
      "tags": "",
      "isDone": true,
      "createdAt": "2026-04-24T18:51:05.733Z",
      "completedAt": "2026-04-24T18:51:22.101Z"
    },
    {
      "id": "e5c66777-120a-4893-b897-340644288e12",
      "userId": 1,
      "title": "test",
      "description": "",
      "priority": "High",
      "dueDate": "2026-04-24",
      "category": "Personal",
      "tags": "",
      "isDone": false,
      "createdAt": "2026-04-24T18:53:06.465Z"
    }
  ]
}